LICENSE
json_mapper/__init__.py
json_mapper/mapper.py
json_position_mapper-0.1.0.dist-info/LICENSE
json_position_mapper-0.1.0.dist-info/WHEEL
json_position_mapper-0.1.0.dist-info/METADATA
json_position_mapper-0.1.0.dist-info/RECORD
