Metadata-Version: 2.1
Name: json-position-mapper
Version: 0.1.0
Summary: Map file-based JSON inputs from the file keys to their locations in the original file
Home-page: https://github.com/atlantistechnology/json-position-mapper
License: MIT
Author: Adam Peacock
Author-email: apeacock@atlantistech.com
Requires-Python: >=3.7,<4
Classifier: Development Status :: 4 - Beta
Classifier: Intended Audience :: Developers
Classifier: License :: OSI Approved :: MIT License
Classifier: Operating System :: OS Independent
Classifier: Programming Language :: Python :: 3
Classifier: Programming Language :: Python :: 3.10
Classifier: Programming Language :: Python :: 3.7
Classifier: Programming Language :: Python :: 3.8
Classifier: Programming Language :: Python :: 3.9
Classifier: Topic :: Software Development :: Libraries :: Python Modules
Requires-Dist: json-stream (>=1.3.0)
Project-URL: Repository, https://github.com/atlantistechnology/json-position-mapper
